code_expert/__init__.py
code_expert/config.py
code_expert/logging_config.py
code_expert/analysis/complexity.py
code_expert/config/config.yaml
code_expert/context/__init__.py
code_expert/context/builder.py
code_expert/context/extended_repo_map.py
code_expert/context/extractor.py
code_expert/context/mock_builder.py
code_expert/mcp/__init__.py
code_expert/mcp/server/__init__.py
code_expert/mcp/server/app.py
code_expert/mcp/server/simple_http_app.py
code_expert/pattern_search/searcher.py
code_expert/repository/__init__.py
code_expert/repository/auto_refresh.py
code_expert/repository/cache.py
code_expert/repository/documentation.py
code_expert/repository/manager.py
code_expert/repository/path_utils.py
code_expert/repository/file_filtering/__init__.py
code_expert/repository/file_filtering/repo_filter.py
code_expert/repository/providers/__init__.py
code_expert/repository/providers/azure_devops.py
code_expert/repository/providers/base.py
code_expert/repository/providers/github.py
code_expert/repository/providers/registry.py
code_expert/resources/language_extensions.txt
code_expert/webhooks/__init__.py
code_expert/webhooks/handler.py
code_expert/webhooks/parsers.py
code_expert/webhooks/security.py
code_expert_mcp-0.3.0.dist-info/METADATA
code_expert_mcp-0.3.0.dist-info/WHEEL
code_expert_mcp-0.3.0.dist-info/entry_points.txt
code_expert_mcp-0.3.0.dist-info/RECORD
